oterogeneity/__init__.py
oterogeneity/oterogeneity.py
oterogeneity/utils.py
oterogeneity-1.0.1.dist-info/METADATA
oterogeneity-1.0.1.dist-info/WHEEL
oterogeneity-1.0.1.dist-info/top_level.txt
oterogeneity-1.0.1.dist-info/RECORD
