Metadata-Version: 2.4
Name: oterogeneity
Version: 1.0.1
Summary: Python library to compute heterogeneity indexes based on optimal transport.
Author: Xavier Bacon
Author-email: Joseph Touzet <joseph.touzet@ens-paris-saclay.fr>
License: CC Attribution 4.0
Project-URL: Repository, https://github.com/jolatechno/ot-heterogeneity
Keywords: optimal transport,geography,segregation,spatial heterogeneity
Requires-Python: >=3.8
Requires-Dist: numpy
Requires-Dist: scikit-learn
Requires-Dist: pot
